{"_type":"export","__export_format":4,"__export_date":"2021-04-19T19:10:11.300Z","__export_source":"insomnia.desktop.app:v2021.2.2","resources":[{"_id":"req_c3bf7b807ee7448a9f77450930f3b961","parentId":"fld_d8a6851f494441bfb55c055175d255ea","modified":1618516653905,"created":1618516644813,"url":"{{ _.urllocal }}/titulos","name":"Listar Titulos","description":"","method":"GET","body":{},"parameters":[],"headers":[],"authentication":{},"metaSortKey":-1618516644813,"isPrivate":false,"settingStoreCookies":true,"settingSendCookies":true,"settingDisableRenderRequestBody":false,"settingEncodeUrl":true,"settingRebuildPath":true,"settingFollowRedirects":"global","_type":"request"},{"_id":"fld_d8a6851f494441bfb55c055175d255ea","parentId":"fld_b4f5fd11a24845268cb9ab6e8a75069d","modified":1618516635629,"created":1618516635629,"name":"Cobranças","description":"","environment":{},"environmentPropertyOrder":null,"metaSortKey":-1618516635630,"_type":"request_group"},{"_id":"fld_b4f5fd11a24845268cb9ab6e8a75069d","parentId":"wrk_b6498cdfcf664793bccde612272e6d24","modified":1618510481470,"created":1618510481470,"name":"API BOLETO","description":"","environment":{},"environmentPropertyOrder":null,"metaSortKey":-1618510481470,"_type":"request_group"},{"_id":"wrk_b6498cdfcf664793bccde612272e6d24","parentId":null,"modified":1618493441685,"created":1611339061317,"name":"My workspace","description":"","scope":"collection","_type":"workspace"},{"_id":"req_acf14f3415854129ae756bb3fe6328d2","parentId":"fld_d8a6851f494441bfb55c055175d255ea","modified":1618516746132,"created":1618516741207,"url":"{{ _.urllocal }}/titulo/1","name":"Listar Titulo","description":"","method":"GET","body":{},"parameters":[],"headers":[],"authentication":{},"metaSortKey":-1618516369124,"isPrivate":false,"settingStoreCookies":true,"settingSendCookies":true,"settingDisableRenderRequestBody":false,"settingEncodeUrl":true,"settingRebuildPath":true,"settingFollowRedirects":"global","_type":"request"},{"_id":"req_9af788070daa43d3933e0b298c32783b","parentId":"fld_d8a6851f494441bfb55c055175d255ea","modified":1618585705693,"created":1618516756952,"url":"{{ _.urllocal }}/titulo","name":"Inserir Titulo","description":"","method":"POST","body":{"mimeType":"application/json","text":"{\n\t\"id_empresa\": 0,\n\t\"id_cliente\": 0,\n\t\"datavencimento\": \"\",\n\t\"datadocumento\": \"\",\n\t\"numerodocumento\": \"\",\n\t\"dataprocessamento\": \"\",\n\t\"nossonumero\": \"\",\n\t\"valordocumento\": 0,\n\t\"valorabatimento\": 0,\n\t\"valormorajuros\": 0,\n\t\"valordesconto\": 0,\n\t\"datamorajuros\": \"\",\n\t\"datadesconto\": \"\",\n\t\"dataabatimento\": \"\",\n\t\"dataprotesto\": \"\",\n\t\"percentualmulto\": 0,\n\t\"tipo\": 0\n}"},"parameters":[],"headers":[{"name":"Content-Type","value":"application/json","id":"pair_46397133f6b748199e714e519dec2206"}],"authentication":{},"metaSortKey":-1618516231279.5,"isPrivate":false,"settingStoreCookies":true,"settingSendCookies":true,"settingDisableRenderRequestBody":false,"settingEncodeUrl":true,"settingRebuildPath":true,"settingFollowRedirects":"global","_type":"request"},{"_id":"req_e6ea1161ca424eaf9802983a93e6b413","parentId":"fld_d8a6851f494441bfb55c055175d255ea","modified":1618591570483,"created":1618586877532,"url":"{{ _.urllocal }}/gerarboleto","name":"GerarBoleto","description":"","method":"POST","body":{"mimeType":"application/json","text":"{\n\t\"id_empresa\": 1,\n\t\"id_cliente\": 1,\n\t\"datavencimento\": \"10/05/2021\",\n\t\"numerodocumento\": \"123456\",\n\t\"nossonumero\": \"1235\",\n\t\"valordocumento\": 50,\n\t\"valormorajuros\": 2,\n\t\"datamorajuros\": \"11/05/2021\",\n\t\"tipo\": 0\n}"},"parameters":[],"headers":[{"name":"Content-Type","value":"application/json","id":"pair_46397133f6b748199e714e519dec2206"}],"authentication":{},"metaSortKey":-1618516196818.375,"isPrivate":false,"settingStoreCookies":true,"settingSendCookies":true,"settingDisableRenderRequestBody":false,"settingEncodeUrl":true,"settingRebuildPath":true,"settingFollowRedirects":"global","_type":"request"},{"_id":"req_a651fd7cd8924bef8baa1f0ac4acb431","parentId":"fld_d8a6851f494441bfb55c055175d255ea","modified":1618855889323,"created":1618855456950,"url":"{{ _.urllocal }}/registraboleto","name":"Registra Boleto","description":"","method":"POST","body":{"mimeType":"application/json","text":"{\n\t\"id_empresa\": 1,\n\t\"id_cliente\": 1,\n\t\"datavencimento\": \"10/05/2021\",\n\t\"numerodocumento\": \"123456\",\n\t\"nossonumero\": \"1235\",\n\t\"valordocumento\": 50,\n\t\"valormorajuros\": 2,\n\t\"valorabatimento\": 0,\n\t\"valoramorajuros\": 0,\n\t\"valoradesconto\": 0,\n\t\"datadesconto\": \"19/05/2021\",\n\t\"dataabatimento\": \"19/05/2021\",\n\t\"dataprotesto\": \"19/05/2021\",\n\t\"percentualmulto\": \"19/05/2021\",\n\t\"datamorajuros\": \"11/05/2021\",\n\t\"tipo\": 0\n}"},"parameters":[],"headers":[{"name":"Content-Type","value":"application/json","id":"pair_46397133f6b748199e714e519dec2206"}],"authentication":{},"metaSortKey":-1618516179587.8125,"isPrivate":false,"settingStoreCookies":true,"settingSendCookies":true,"settingDisableRenderRequestBody":false,"settingEncodeUrl":true,"settingRebuildPath":true,"settingFollowRedirects":"global","_type":"request"},{"_id":"req_33c1bd92e55c4a6f9a16584c835c26e1","parentId":"fld_d8a6851f494441bfb55c055175d255ea","modified":1618517233986,"created":1618517223474,"url":"{{ _.urllocal }}/titulo/:id","name":"Alterar Titulo","description":"","method":"PUT","body":{"mimeType":"application/json","text":"{\n\t\"id_empresa\": 0,\n\t\"id_cliente\": 0,\n\t\"datavencimento\": \"\",\n\t\"datadocumento\": \"\",\n\t\"numerodocumento\": \"\",\n\t\"dataprocessamento\": \"\",\n\t\"nossonumero\": \"\",\n\t\"valordocumento\": 0,\n\t\"valorabatimento\": 0,\n\t\"valormorajuros\": 0,\n\t\"datamorajuros\": \"\",\n\t\"datadesconto\": \"\",\n\t\"dataabatimento\": \"\",\n\t\"dataprotesto\": \"\",\n\t\"percentualmulto\": 0,\n\t\"tipo\": 0\n}"},"parameters":[],"headers":[{"name":"Content-Type","value":"application/json","id":"pair_46397133f6b748199e714e519dec2206"}],"authentication":{},"metaSortKey":-1618516162357.25,"isPrivate":false,"settingStoreCookies":true,"settingSendCookies":true,"settingDisableRenderRequestBody":false,"settingEncodeUrl":true,"settingRebuildPath":true,"settingFollowRedirects":"global","_type":"request"},{"_id":"req_226773d2493641968cb4cadf82b77d21","parentId":"fld_d8a6851f494441bfb55c055175d255ea","modified":1618517253285,"created":1618517245834,"url":"{{ _.urllocal }}/titulo/:id","name":"Apagar Titulo","description":"","method":"DELETE","body":{},"parameters":[],"headers":[],"authentication":{},"metaSortKey":-1618516127896.125,"isPrivate":false,"settingStoreCookies":true,"settingSendCookies":true,"settingDisableRenderRequestBody":false,"settingEncodeUrl":true,"settingRebuildPath":true,"settingFollowRedirects":"global","_type":"request"},{"_id":"req_82126064f5c34691b55f16657f1bb66e","parentId":"fld_0ed748d69d00471abf2e763b5d31d3cd","modified":1618516120478,"created":1618516093435,"url":"{{ _.urllocal }}/clientes","name":"Lista Clientes","description":"","method":"GET","body":{},"parameters":[],"headers":[],"authentication":{},"metaSortKey":-1618516093435,"isPrivate":false,"settingStoreCookies":true,"settingSendCookies":true,"settingDisableRenderRequestBody":false,"settingEncodeUrl":true,"settingRebuildPath":true,"settingFollowRedirects":"global","_type":"request"},{"_id":"fld_0ed748d69d00471abf2e763b5d31d3cd","parentId":"fld_b4f5fd11a24845268cb9ab6e8a75069d","modified":1618516083477,"created":1618516083477,"name":"Dados Cadastrais","description":"","environment":{},"environmentPropertyOrder":null,"metaSortKey":-1618516083477,"_type":"request_group"},{"_id":"req_8979dc13dc2d480dbfe2c3cc61d4d274","parentId":"fld_0ed748d69d00471abf2e763b5d31d3cd","modified":1618516133726,"created":1618516130776,"url":"{{ _.urllocal }}/cliente","name":"Lista Cliente","description":"","method":"GET","body":{},"parameters":[],"headers":[],"authentication":{},"metaSortKey":-1618515836890.5,"isPrivate":false,"settingStoreCookies":true,"settingSendCookies":true,"settingDisableRenderRequestBody":false,"settingEncodeUrl":true,"settingRebuildPath":true,"settingFollowRedirects":"global","_type":"request"},{"_id":"req_5c8ad163825e4fbeb0c2c182be4c2f42","parentId":"fld_0ed748d69d00471abf2e763b5d31d3cd","modified":1618589441129,"created":1618516144162,"url":"{{ _.urllocal }}/cliente","name":"Inserir Cliente","description":"","method":"POST","body":{"mimeType":"application/json","text":"{\n\t\"nome\": \"Anthony Julio Nogueira\",\n\t\"cpfcnpj\": \"924.833.087-83\",\n\t\"tipo\": 0,\n\t\"logradouro\": \"Rua Jose Avelino de Morais\",\n\t\"numero\": \"498\",\n\t\"cep\": \"26150-330\",\n\t\"bairro\": \"Novo Eldorado\",\n\t\"cidade\": \"Belford Roxo\",\n\t\"uf\": \"RJ\",\n\t\"telefone\": \"(21) 2996-2396 / (21) 99309-8562\",\n\t\"email\": \"anthonyjulionogueira_@grupoitaipu.com.br\"\n}"},"parameters":[],"headers":[{"name":"Content-Type","value":"application/json","id":"pair_9d01849d16dc4229a6934a8c6bd59c20"}],"authentication":{},"metaSortKey":-1618515708618.25,"isPrivate":false,"settingStoreCookies":true,"settingSendCookies":true,"settingDisableRenderRequestBody":false,"settingEncodeUrl":true,"settingRebuildPath":true,"settingFollowRedirects":"global","_type":"request"},{"_id":"req_d94557a30f1b4860ae1604922c60ea54","parentId":"fld_0ed748d69d00471abf2e763b5d31d3cd","modified":1618517282410,"created":1618516168454,"url":"{{ _.urllocal }}/cliente/:id","name":"Atualizar Cliente","description":"","method":"PUT","body":{"mimeType":"application/json","text":"{\n\t\"nome\": \"\",\n\t\"nome\": \"\",\n\t\"cpfcnpj\": \"\",\n\t\"tipo\": 0,\n\t\"logradouro\": \"\",\n\t\"numero\": \"\",\n\t\"cep\": \"\",\n\t\"cidade\": \"\",\n\t\"uf\": \"\",\n\t\"complemento\": \"\",\n\t\"telefone\": \"\",\n\t\"email\": \"\",\n\t\"telefone\": \"\",\n\t\"mensagem\": \"\"\n}"},"parameters":[],"headers":[{"name":"Content-Type","value":"application/json","id":"pair_ff3daef1a00546a086cdc059b5c9787f"}],"authentication":{},"metaSortKey":-1618515644482.125,"isPrivate":false,"settingStoreCookies":true,"settingSendCookies":true,"settingDisableRenderRequestBody":false,"settingEncodeUrl":true,"settingRebuildPath":true,"settingFollowRedirects":"global","_type":"request"},{"_id":"req_d44db8a5dd7446448469cc0fe4344b3c","parentId":"fld_0ed748d69d00471abf2e763b5d31d3cd","modified":1618517288448,"created":1618516185479,"url":"{{ _.urllocal }}/cliente/:id","name":"Apagar Cliente","description":"","method":"DELETE","body":{},"parameters":[],"headers":[],"authentication":{},"metaSortKey":-1618515612414.0625,"isPrivate":false,"settingStoreCookies":true,"settingSendCookies":true,"settingDisableRenderRequestBody":false,"settingEncodeUrl":true,"settingRebuildPath":true,"settingFollowRedirects":"global","_type":"request"},{"_id":"req_75e91be84a4d4b0db00f09cca54f3b76","parentId":"fld_0ed748d69d00471abf2e763b5d31d3cd","modified":1618516488279,"created":1618516205235,"url":"{{ _.urllocal }}/empresas","name":"Lista Empresas","description":"","method":"GET","body":{},"parameters":[],"headers":[],"authentication":{},"metaSortKey":-1618515596330.0312,"isPrivate":false,"settingStoreCookies":true,"settingSendCookies":true,"settingDisableRenderRequestBody":false,"settingEncodeUrl":true,"settingRebuildPath":true,"settingFollowRedirects":"global","_type":"request"},{"_id":"req_50f9e96429564a1bb0be0313cfb3ced5","parentId":"fld_0ed748d69d00471abf2e763b5d31d3cd","modified":1618516491082,"created":1618516217500,"url":"{{ _.urllocal }}/empresa/1","name":"Lista Empresa","description":"","method":"GET","body":{},"parameters":[],"headers":[],"authentication":{},"metaSortKey":-1618515596280.0312,"isPrivate":false,"settingStoreCookies":true,"settingSendCookies":true,"settingDisableRenderRequestBody":false,"settingEncodeUrl":true,"settingRebuildPath":true,"settingFollowRedirects":"global","_type":"request"},{"_id":"req_6fb603cac5a94f2c8e4300a3610bdd5b","parentId":"fld_0ed748d69d00471abf2e763b5d31d3cd","modified":1618589165817,"created":1618516246629,"url":"{{ _.urllocal }}/empresa","name":"Inserir Empresa","description":"","method":"POST","body":{"mimeType":"application/json","text":"{\n\t\"nome\": \"Rodrigo e Evelyn Buffet ME\",\n\t\"fantasia\": \"Rodrigo e Evelyn Buffet ME\",\n\t\"cpfcnpj\": \"03.393.410/0001-38\",\n\t\"tipo\": \"JURIDICA\",\n\t\"logradouro\": \"Avenida Carioca\",\n\t\"numero\": \"116\",\n\t\"cep\": \"25510-161\",\n\t\"cidade\": \"Sao Joao de Meriti\",\n\t\"uf\": \"RJ\",\n\t\"complemento\": \"\",\n\t\"telefone\": \"(21) 3989-3715 / (21) 99281-0251\"\n}"},"parameters":[],"headers":[{"name":"Content-Type","value":"application/json","id":"pair_9b1308db407c4032915b60ff15c2a0bc"}],"authentication":{},"metaSortKey":-1618515596230.0312,"isPrivate":false,"settingStoreCookies":true,"settingSendCookies":true,"settingDisableRenderRequestBody":false,"settingEncodeUrl":true,"settingRebuildPath":true,"settingFollowRedirects":"global","_type":"request"},{"_id":"req_3d6d58ddfc184e4da51b2f024ef4c756","parentId":"fld_0ed748d69d00471abf2e763b5d31d3cd","modified":1618517295207,"created":1618516410209,"url":"{{ _.urllocal }}/empresa/:id","name":"Atualizar Empresa","description":"","method":"PUT","body":{"mimeType":"application/json","text":"{\n\t\"nome\": \"\",\n\t\"fantasia\": \"\",\n\t\"cpfcnpj\": \"\",\n\t\"tipo\": \"\",\n\t\"logradouro\": \"\",\n\t\"numero\": \"\",\n\t\"cep\": \"\",\n\t\"cidade\": \"\",\n\t\"uf\": \"\",\n\t\"complemento\": \"\",\n\t\"telefone\": \"\"\n}"},"parameters":[],"headers":[{"name":"Content-Type","value":"application/json","id":"pair_6cab142e53ce42c2b8782558e157f734"}],"authentication":{},"metaSortKey":-1618515596180.0312,"isPrivate":false,"settingStoreCookies":true,"settingSendCookies":true,"settingDisableRenderRequestBody":false,"settingEncodeUrl":true,"settingRebuildPath":true,"settingFollowRedirects":"global","_type":"request"},{"_id":"req_09acccd9b4b04553bcd97d8759a5f6da","parentId":"fld_0ed748d69d00471abf2e763b5d31d3cd","modified":1618517299572,"created":1618516474211,"url":"{{ _.urllocal }}/empresa/:id","name":"Apagar Empresa","description":"","method":"DELETE","body":{},"parameters":[],"headers":[],"authentication":{},"metaSortKey":-1618515596130.0312,"isPrivate":false,"settingStoreCookies":true,"settingSendCookies":true,"settingDisableRenderRequestBody":false,"settingEncodeUrl":true,"settingRebuildPath":true,"settingFollowRedirects":"global","_type":"request"},{"_id":"req_0c2c4599eaf647e18bfabf094b83b548","parentId":"fld_654e880592e348cebda61d30959c73f7","modified":1618515605979,"created":1618515580295,"url":"{{ _.urllocal }}/configuracoes","name":"Lista configuracões","description":"","method":"GET","body":{},"parameters":[],"headers":[],"authentication":{},"metaSortKey":-1618515580346,"isPrivate":false,"settingStoreCookies":true,"settingSendCookies":true,"settingDisableRenderRequestBody":false,"settingEncodeUrl":true,"settingRebuildPath":true,"settingFollowRedirects":"global","_type":"request"},{"_id":"fld_654e880592e348cebda61d30959c73f7","parentId":"fld_b4f5fd11a24845268cb9ab6e8a75069d","modified":1618515569640,"created":1618515569640,"name":"Configuração","description":"","environment":{},"environmentPropertyOrder":null,"metaSortKey":-1618515569640,"_type":"request_group"},{"_id":"req_7f840598dce646c89b19eb9292cfbc4d","parentId":"fld_654e880592e348cebda61d30959c73f7","modified":1618515673102,"created":1618515628711,"url":"{{ _.urllocal }}/configuracao/1","name":"Lista configuração","description":"","method":"GET","body":{},"parameters":[],"headers":[],"authentication":{},"metaSortKey":-1618504468699.5,"isPrivate":false,"settingStoreCookies":true,"settingSendCookies":true,"settingDisableRenderRequestBody":false,"settingEncodeUrl":true,"settingRebuildPath":true,"settingFollowRedirects":"global","_type":"request"},{"_id":"req_df4a96525766450b858d80712e7d7f59","parentId":"fld_654e880592e348cebda61d30959c73f7","modified":1618591426326,"created":1618515653977,"url":"{{ _.urllocal }}/configuracao","name":"Insere configuração","description":"","method":"POST","body":{"mimeType":"application/json","text":"{\n\t\"id_empresa\": 1,\n\t\"tipocobranca\": 6,\n\t\"codbanco\": \"341\",\n\t\"agencia\": \"8492\",\n\t\"conta\": \"82980\",\n\t\"contadig\": \"2\",\n\t\"codigocedente\": \"4266443\",\n\t\"carteira\": \"09\",\n\t\"especiedoc\": \"DM\",\n\t\"especiemod\": \"$\",\n\t\"aceite\": 0,\n\t\"localpagamento\": \"Pagar preferencialmente nas agencias Itau\",\n\t\"dirarqremessa\": \"c:\\temp\",\n\t\"dirarqretorno\": \"c:\\temp\",\n\t\"layoutremessa\": \"0\"\n}"},"parameters":[],"headers":[{"name":"Content-Type","value":"application/json","id":"pair_5a14da9ab50f49118164520032bda899"}],"authentication":{},"metaSortKey":-1618498912876.25,"isPrivate":false,"settingStoreCookies":true,"settingSendCookies":true,"settingDisableRenderRequestBody":false,"settingEncodeUrl":true,"settingRebuildPath":true,"settingFollowRedirects":"global","_type":"request"},{"_id":"req_41da1ccd343a41cabd7cd2dd2c1fc321","parentId":"fld_654e880592e348cebda61d30959c73f7","modified":1618517307350,"created":1618516020985,"url":"{{ _.urllocal }}/configuracao/:id","name":"Atualiza configuração","description":"","method":"PUT","body":{"mimeType":"application/json","text":"{\n\t\"tipocobranca\": 0,\n\t\"codbanco\": \"\",\n\t\"agencia\": \"\",\n\t\"agenciadig\": \"\",\n\t\"conta\": \"\",\n\t\"contadig\": \"\",\n\t\"codigocedente\": \"\",\n\t\"convenio\": \"\",\n\t\"carteira\": \"\",\n\t\"modalidade\": \"\",\n\t\"especiedoc\": \"\",\n\t\"especiemod\": \"\",\n\t\"aceite\": 0,\n\t\"localpagamento\": \"\",\n\t\"dirarqremessa\": \"\",\n\t\"dirarqretorno\": \"\",\n\t\"layoutremessa\": \"\",\n\t\"nomearqremessa\": \"\",\n\t\"nomearqretorno\": \"\",\n\t\"instrucao1\": \"\",\n\t\"instrucao2\": \"\",\n\t\"arquivologo\": \"\"\n}"},"parameters":[],"headers":[{"name":"Content-Type","value":"application/json","id":"pair_5a14da9ab50f49118164520032bda899"}],"authentication":{},"metaSortKey":-1618496134964.625,"isPrivate":false,"settingStoreCookies":true,"settingSendCookies":true,"settingDisableRenderRequestBody":false,"settingEncodeUrl":true,"settingRebuildPath":true,"settingFollowRedirects":"global","_type":"request"},{"_id":"req_acd4ff5e6fe0471b807d533a2058718b","parentId":"fld_654e880592e348cebda61d30959c73f7","modified":1618517311230,"created":1618516048320,"url":"{{ _.urllocal }}/configuracao/:id","name":"Apagar configuração","description":"","method":"DELETE","body":{"mimeType":"application/json","text":"{\n\t\"tipocobranca\": 0,\n\t\"codbanco\": \"\",\n\t\"agencia\": \"\",\n\t\"agenciadig\": \"\",\n\t\"conta\": \"\",\n\t\"contadig\": \"\",\n\t\"codigocedente\": \"\",\n\t\"convenio\": \"\",\n\t\"carteira\": \"\",\n\t\"modalidade\": \"\",\n\t\"especiedoc\": \"\",\n\t\"especiemod\": \"\",\n\t\"aceite\": 0,\n\t\"localpagamento\": \"\",\n\t\"dirarqremessa\": \"\",\n\t\"dirarqretorno\": \"\",\n\t\"layoutremessa\": \"\",\n\t\"nomearqremessa\": \"\",\n\t\"nomearqretorno\": \"\",\n\t\"instrucao1\": \"\",\n\t\"instrucao2\": \"\",\n\t\"arquivologo\": \"\"\n}"},"parameters":[],"headers":[{"name":"Content-Type","value":"application/json","id":"pair_5a14da9ab50f49118164520032bda899"}],"authentication":{},"metaSortKey":-1618494746008.8125,"isPrivate":false,"settingStoreCookies":true,"settingSendCookies":true,"settingDisableRenderRequestBody":false,"settingEncodeUrl":true,"settingRebuildPath":true,"settingFollowRedirects":"global","_type":"request"},{"_id":"env_fc9ce11fa792831790aa31c2641bc0aa103e58df","parentId":"wrk_b6498cdfcf664793bccde612272e6d24","modified":1618494565810,"created":1611339061404,"name":"Base Environment","data":{"base_url":"https://api.mercadopago.com/users/","collector_id":"17552238","access_token":"APP_USR-8656261441103947-020220-7aee7ec199adcbd1f4fc047883053119-17552238","urllocal":"http://localhost:9000"},"dataPropertyOrder":{"&":["base_url","collector_id","access_token","urllocal"]},"color":null,"isPrivate":false,"metaSortKey":1611339061404,"_type":"environment"},{"_id":"jar_fc9ce11fa792831790aa31c2641bc0aa103e58df","parentId":"wrk_b6498cdfcf664793bccde612272e6d24","modified":1611339061409,"created":1611339061409,"name":"Default Jar","cookies":[],"_type":"cookie_jar"},{"_id":"spc_09a1b5ecf08042778641801e4f923b50","parentId":"wrk_b6498cdfcf664793bccde612272e6d24","modified":1611339061321,"created":1611339061321,"fileName":"Insomnia","contents":"","contentType":"yaml","_type":"api_spec"}]}